microbiome_analysis/__init__.py
microbiome_analysis/beta_diversity.py
microbiome_analysis/classification.py
microbiome_analysis/dashboard.py
microbiome_analysis/diversity.py
microbiome_analysis/network.py
microbiome_analysis/normalization.py
microbiome_analysis/preprocessing.py
microbiome_analysis/qc.py
microbiome_analysis/statistics.py
microbiome_analysis/visualization.py
test/__init__.py
test/test_classification.py
test/test_diversity.py
test/test_network.py
test/test_normalization.py
test/test_preprocessing.py
test/test_statistics.py
test/test_visualization.py
microbiome_analysis-0.1.2.dist-info/LICENSE
microbiome_analysis-0.1.2.dist-info/METADATA
microbiome_analysis-0.1.2.dist-info/WHEEL
microbiome_analysis-0.1.2.dist-info/top_level.txt
microbiome_analysis-0.1.2.dist-info/RECORD
